{
  "type": [
    "h-entry"
  ],
  "properties": {
    "content": [
      "Previous series of The Walking Dead disappeared from Sky Box Sets today. Found them on Amazon Prime video instead. Bad form, @SkyHelpTeam."
    ],
    "category": [
      "tv",
      "uk",
      "thewalkingdead",
      "sky",
      "amazon"
    ],
    "syndication": [
      "https://twitter.com/barryf/status/848269786421362689"
    ],
    "entry-type": [
      "note"
    ],
    "published": [
      "2017-04-01T20:24:12Z"
    ]
  }
}