{
  "type": [
    "h-cite"
  ],
  "properties": {
    "url": [
      "https://twitter.com/manuelpueyo/status/885812200908181505"
    ],
    "name": [
      "Absolutely . Lets catch up next week @HwcBrussels"
    ],
    "published": [
      "2017-07-14T10:44:20Z"
    ],
    "author": [
      "http://web.manuelpueyo.tech/"
    ],
    "in-reply-to": [
      "https://barryfrost.com/2017/07/homebrew-website-club-london-group-photo"
    ],
    "content": [
      "Absolutely . Lets catch up next week @HwcBrussels"
    ]
  }
}